MANIFEST.in
setup.py
fragment/__init__.py
fragment/fragment.py
fragment/index.html
fragment/single.html
fragment/style.css
fragment.egg-info/PKG-INFO
fragment.egg-info/SOURCES.txt
fragment.egg-info/dependency_links.txt
fragment.egg-info/entry_points.txt
fragment.egg-info/requires.txt
fragment.egg-info/top_level.txt