Metadata-Version: 1.0
Name: fragment
Version: 0.0.2
Summary: just another static site generator
Home-page: https://github.com/zweifisch/fragment
Author: Feng Zhou
Author-email: zf.pascal@gmail.com
License: UNKNOWN
Platform: UNKNOWN
